MANIFEST.in
README.rst
requirements.txt
setup.py
check_no_scheduled_ec2_events/__init__.py
check_no_scheduled_ec2_events.egg-info/PKG-INFO
check_no_scheduled_ec2_events.egg-info/SOURCES.txt
check_no_scheduled_ec2_events.egg-info/dependency_links.txt
check_no_scheduled_ec2_events.egg-info/entry_points.txt
check_no_scheduled_ec2_events.egg-info/pbr.json
check_no_scheduled_ec2_events.egg-info/requires.txt
check_no_scheduled_ec2_events.egg-info/top_level.txt