Metadata-Version: 1.0
Name: check-no-scheduled-ec2-events
Version: 0.2.1
Summary: Nagios-style check if the current EC2 instance has any scheduled events
Home-page: http://github.com/martinmelin/check_no_scheduled_ec2_events
Author: Martin Melin
Author-email: martin@tictail.com
License: Creative Commons Attribution-Noncommercial-Share Alike license
Platform: UNKNOWN
